{
  "version": "6",
  "dialect": "sqlite",
  "id": "8ab6aca8-52a3-461b-9a6a-2a4509377949",
  "prevId": "00000000-0000-0000-0000-000000000000",
  "tables": {
    "resource": {
      "name": "resource",
      "columns": {
        "id": {
          "name": "id",
          "type": "integer",
          "primaryKey": true,
          "notNull": true,
          "autoincrement": true
        },
        "remark": {
          "name": "remark",
          "type": "text",
          "primaryKey": false,
          "notNull": false,
          "autoincrement": false
        },
        "sort": {
          "name": "sort",
          "type": "integer",
          "primaryKey": false,
          "notNull": true,
          "autoincrement": false,
          "default": 0
        },
        "del_flag": {
          "name": "del_flag",
          "type": "text",
          "primaryKey": false,
          "notNull": true,
          "autoincrement": false,
          "default": "'N'"
        },
        "created_at": {
          "name": "created_at",
          "type": "integer",
          "primaryKey": false,
          "notNull": true,
          "autoincrement": false,
          "default": 1729826524765
        },
        "updated_at": {
          "name": "updated_at",
          "type": "integer",
          "primaryKey": false,
          "notNull": true,
          "autoincrement": false,
          "default": 1729826524765
        },
        "created_by": {
          "name": "created_by",
          "type": "text",
          "primaryKey": false,
          "notNull": true,
          "autoincrement": false
        },
        "updated_by": {
          "name": "updated_by",
          "type": "text",
          "primaryKey": false,
          "notNull": true,
          "autoincrement": false
        },
        "status": {
          "name": "status",
          "type": "text",
          "primaryKey": false,
          "notNull": true,
          "autoincrement": false,
          "default": "'N'"
        },
        "parent_id": {
          "name": "parent_id",
          "type": "integer",
          "primaryKey": false,
          "notNull": true,
          "autoincrement": false
        },
        "resource_code": {
          "name": "resource_code",
          "type": "text",
          "primaryKey": false,
          "notNull": true,
          "autoincrement": false
        },
        "resource_name_en": {
          "name": "resource_name_en",
          "type": "text",
          "primaryKey": false,
          "notNull": true,
          "autoincrement": false
        },
        "resource_name_zh_cn": {
          "name": "resource_name_zh_cn",
          "type": "text",
          "primaryKey": false,
          "notNull": true,
          "autoincrement": false
        },
        "resource_type": {
          "name": "resource_type",
          "type": "text",
          "primaryKey": false,
          "notNull": true,
          "autoincrement": false
        },
        "path": {
          "name": "path",
          "type": "text",
          "primaryKey": false,
          "notNull": false,
          "autoincrement": false
        },
        "active_path": {
          "name": "active_path",
          "type": "text",
          "primaryKey": false,
          "notNull": false,
          "autoincrement": false
        },
        "component": {
          "name": "component",
          "type": "text",
          "primaryKey": false,
          "notNull": false,
          "autoincrement": false
        },
        "icon": {
          "name": "icon",
          "type": "text",
          "primaryKey": false,
          "notNull": false,
          "autoincrement": false
        },
        "is_link": {
          "name": "is_link",
          "type": "text",
          "primaryKey": false,
          "notNull": true,
          "autoincrement": false
        },
        "is_cache": {
          "name": "is_cache",
          "type": "text",
          "primaryKey": false,
          "notNull": true,
          "autoincrement": false
        },
        "is_affix": {
          "name": "is_affix",
          "type": "text",
          "primaryKey": false,
          "notNull": true,
          "autoincrement": false
        },
        "is_hide": {
          "name": "is_hide",
          "type": "text",
          "primaryKey": false,
          "notNull": true,
          "autoincrement": false
        }
      },
      "indexes": {
        "resource_resource_code_unique": {
          "name": "resource_resource_code_unique",
          "columns": ["resource_code"],
          "isUnique": true
        }
      },
      "foreignKeys": {},
      "compositePrimaryKeys": {},
      "uniqueConstraints": {}
    },
    "role_to_resource": {
      "name": "role_to_resource",
      "columns": {
        "id": {
          "name": "id",
          "type": "integer",
          "primaryKey": true,
          "notNull": true,
          "autoincrement": true
        },
        "remark": {
          "name": "remark",
          "type": "text",
          "primaryKey": false,
          "notNull": false,
          "autoincrement": false
        },
        "sort": {
          "name": "sort",
          "type": "integer",
          "primaryKey": false,
          "notNull": true,
          "autoincrement": false,
          "default": 0
        },
        "del_flag": {
          "name": "del_flag",
          "type": "text",
          "primaryKey": false,
          "notNull": true,
          "autoincrement": false,
          "default": "'N'"
        },
        "created_at": {
          "name": "created_at",
          "type": "integer",
          "primaryKey": false,
          "notNull": true,
          "autoincrement": false,
          "default": 1729826524765
        },
        "updated_at": {
          "name": "updated_at",
          "type": "integer",
          "primaryKey": false,
          "notNull": true,
          "autoincrement": false,
          "default": 1729826524765
        },
        "created_by": {
          "name": "created_by",
          "type": "text",
          "primaryKey": false,
          "notNull": true,
          "autoincrement": false
        },
        "updated_by": {
          "name": "updated_by",
          "type": "text",
          "primaryKey": false,
          "notNull": true,
          "autoincrement": false
        },
        "role_code": {
          "name": "role_code",
          "type": "text",
          "primaryKey": false,
          "notNull": true,
          "autoincrement": false
        },
        "resource_code": {
          "name": "resource_code",
          "type": "text",
          "primaryKey": false,
          "notNull": true,
          "autoincrement": false
        }
      },
      "indexes": {
        "role_to_resource_unique": {
          "name": "role_to_resource_unique",
          "columns": ["role_code", "resource_code"],
          "isUnique": true
        }
      },
      "foreignKeys": {
        "role_to_resource_role_code_role_role_code_fk": {
          "name": "role_to_resource_role_code_role_role_code_fk",
          "tableFrom": "role_to_resource",
          "tableTo": "role",
          "columnsFrom": ["role_code"],
          "columnsTo": ["role_code"],
          "onDelete": "no action",
          "onUpdate": "no action"
        },
        "role_to_resource_resource_code_resource_resource_code_fk": {
          "name": "role_to_resource_resource_code_resource_resource_code_fk",
          "tableFrom": "role_to_resource",
          "tableTo": "resource",
          "columnsFrom": ["resource_code"],
          "columnsTo": ["resource_code"],
          "onDelete": "no action",
          "onUpdate": "no action"
        }
      },
      "compositePrimaryKeys": {},
      "uniqueConstraints": {}
    },
    "role": {
      "name": "role",
      "columns": {
        "id": {
          "name": "id",
          "type": "integer",
          "primaryKey": true,
          "notNull": true,
          "autoincrement": true
        },
        "remark": {
          "name": "remark",
          "type": "text",
          "primaryKey": false,
          "notNull": false,
          "autoincrement": false
        },
        "sort": {
          "name": "sort",
          "type": "integer",
          "primaryKey": false,
          "notNull": true,
          "autoincrement": false,
          "default": 0
        },
        "del_flag": {
          "name": "del_flag",
          "type": "text",
          "primaryKey": false,
          "notNull": true,
          "autoincrement": false,
          "default": "'N'"
        },
        "created_at": {
          "name": "created_at",
          "type": "integer",
          "primaryKey": false,
          "notNull": true,
          "autoincrement": false,
          "default": 1729826524765
        },
        "updated_at": {
          "name": "updated_at",
          "type": "integer",
          "primaryKey": false,
          "notNull": true,
          "autoincrement": false,
          "default": 1729826524765
        },
        "created_by": {
          "name": "created_by",
          "type": "text",
          "primaryKey": false,
          "notNull": true,
          "autoincrement": false
        },
        "updated_by": {
          "name": "updated_by",
          "type": "text",
          "primaryKey": false,
          "notNull": true,
          "autoincrement": false
        },
        "status": {
          "name": "status",
          "type": "text",
          "primaryKey": false,
          "notNull": true,
          "autoincrement": false,
          "default": "'N'"
        },
        "role_code": {
          "name": "role_code",
          "type": "text",
          "primaryKey": false,
          "notNull": true,
          "autoincrement": false
        },
        "role_name": {
          "name": "role_name",
          "type": "text",
          "primaryKey": false,
          "notNull": true,
          "autoincrement": false
        }
      },
      "indexes": {
        "role_role_code_unique": {
          "name": "role_role_code_unique",
          "columns": ["role_code"],
          "isUnique": true
        }
      },
      "foreignKeys": {},
      "compositePrimaryKeys": {},
      "uniqueConstraints": {}
    },
    "user_to_role": {
      "name": "user_to_role",
      "columns": {
        "id": {
          "name": "id",
          "type": "integer",
          "primaryKey": true,
          "notNull": true,
          "autoincrement": true
        },
        "remark": {
          "name": "remark",
          "type": "text",
          "primaryKey": false,
          "notNull": false,
          "autoincrement": false
        },
        "sort": {
          "name": "sort",
          "type": "integer",
          "primaryKey": false,
          "notNull": true,
          "autoincrement": false,
          "default": 0
        },
        "del_flag": {
          "name": "del_flag",
          "type": "text",
          "primaryKey": false,
          "notNull": true,
          "autoincrement": false,
          "default": "'N'"
        },
        "created_at": {
          "name": "created_at",
          "type": "integer",
          "primaryKey": false,
          "notNull": true,
          "autoincrement": false,
          "default": 1729826524765
        },
        "updated_at": {
          "name": "updated_at",
          "type": "integer",
          "primaryKey": false,
          "notNull": true,
          "autoincrement": false,
          "default": 1729826524765
        },
        "created_by": {
          "name": "created_by",
          "type": "text",
          "primaryKey": false,
          "notNull": true,
          "autoincrement": false
        },
        "updated_by": {
          "name": "updated_by",
          "type": "text",
          "primaryKey": false,
          "notNull": true,
          "autoincrement": false
        },
        "username": {
          "name": "username",
          "type": "text",
          "primaryKey": false,
          "notNull": true,
          "autoincrement": false
        },
        "role_code": {
          "name": "role_code",
          "type": "text",
          "primaryKey": false,
          "notNull": true,
          "autoincrement": false
        }
      },
      "indexes": {
        "user_to_role_unique": {
          "name": "user_to_role_unique",
          "columns": ["username", "role_code"],
          "isUnique": true
        }
      },
      "foreignKeys": {
        "user_to_role_username_user_username_fk": {
          "name": "user_to_role_username_user_username_fk",
          "tableFrom": "user_to_role",
          "tableTo": "user",
          "columnsFrom": ["username"],
          "columnsTo": ["username"],
          "onDelete": "no action",
          "onUpdate": "no action"
        },
        "user_to_role_role_code_role_role_code_fk": {
          "name": "user_to_role_role_code_role_role_code_fk",
          "tableFrom": "user_to_role",
          "tableTo": "role",
          "columnsFrom": ["role_code"],
          "columnsTo": ["role_code"],
          "onDelete": "no action",
          "onUpdate": "no action"
        }
      },
      "compositePrimaryKeys": {},
      "uniqueConstraints": {}
    },
    "user": {
      "name": "user",
      "columns": {
        "id": {
          "name": "id",
          "type": "integer",
          "primaryKey": true,
          "notNull": true,
          "autoincrement": true
        },
        "remark": {
          "name": "remark",
          "type": "text",
          "primaryKey": false,
          "notNull": false,
          "autoincrement": false
        },
        "sort": {
          "name": "sort",
          "type": "integer",
          "primaryKey": false,
          "notNull": true,
          "autoincrement": false,
          "default": 0
        },
        "del_flag": {
          "name": "del_flag",
          "type": "text",
          "primaryKey": false,
          "notNull": true,
          "autoincrement": false,
          "default": "'N'"
        },
        "created_at": {
          "name": "created_at",
          "type": "integer",
          "primaryKey": false,
          "notNull": true,
          "autoincrement": false,
          "default": 1729826524765
        },
        "updated_at": {
          "name": "updated_at",
          "type": "integer",
          "primaryKey": false,
          "notNull": true,
          "autoincrement": false,
          "default": 1729826524765
        },
        "created_by": {
          "name": "created_by",
          "type": "text",
          "primaryKey": false,
          "notNull": true,
          "autoincrement": false
        },
        "updated_by": {
          "name": "updated_by",
          "type": "text",
          "primaryKey": false,
          "notNull": true,
          "autoincrement": false
        },
        "status": {
          "name": "status",
          "type": "text",
          "primaryKey": false,
          "notNull": true,
          "autoincrement": false,
          "default": "'N'"
        },
        "username": {
          "name": "username",
          "type": "text",
          "primaryKey": false,
          "notNull": true,
          "autoincrement": false
        },
        "password": {
          "name": "password",
          "type": "text",
          "primaryKey": false,
          "notNull": true,
          "autoincrement": false
        },
        "is_admin": {
          "name": "is_admin",
          "type": "text",
          "primaryKey": false,
          "notNull": true,
          "autoincrement": false,
          "default": "'N'"
        },
        "last_sign_in_at": {
          "name": "last_sign_in_at",
          "type": "integer",
          "primaryKey": false,
          "notNull": false,
          "autoincrement": false
        }
      },
      "indexes": {
        "user_username_unique": {
          "name": "user_username_unique",
          "columns": ["username"],
          "isUnique": true
        }
      },
      "foreignKeys": {},
      "compositePrimaryKeys": {},
      "uniqueConstraints": {}
    }
  },
  "enums": {},
  "_meta": {
    "schemas": {},
    "tables": {},
    "columns": {}
  },
  "internal": {
    "indexes": {}
  }
}
